{
  "collection": "subtest",
  "pageType": "ToggleGridWithTimer",
  "pageId": "Syllables",
  "enumeratorHelp" : "<p><i>Yambani kuwerengera nthawi pamene ophunzira wawerenga phatikizo loyamba. Yendetsani pensulo ndi kuchonga moyenera yankho lolakwa pogwiritsa ntchito pensulo polemba chizikiro ichi ( / ). Werengerani yozikonza yekha ngati yolondola. Ngati mwachonga kale mayankho odzikonza yekha ngati olakwa, zunguzani mzere pa phatikizolo ndi kupitiriza. Khalani chete pokapokha akamapereka mayankho motere: ngati ophunzira adodoma kuyankha pa masekondi atatu, lozani phatikizo lotsatira ndi kunena, pitiriza. Izi ziyenera kuchitika kamodzi kokha.Chongani phatikizo lomwe mwapereka kwa mwana.</i></p><p><b>PAKATHA MASEKONDI MAKUMI ASANU NDI LIMODZI</b> nenani &ldquo;lekeza pomwepo.&rdquo; Chongani phatikizolomalizira ndi chizindikiro ichi (I) PAKUTHA PA MASEKONDI 60 NENANI &ldquo;lekeza pomwepo&rdquo;).<br><u>Lamulo loyamba:</u> Ngati ophunzira alephere kupereka yankho lolondola limodzi mu mzere woyamba, nenani &ldquo;Zikomo&rdquo;siyilani pomwepo ntchitoyi ndipo chongani mu kabokosi komwe kali pamapeto ndi kupitiriza ndi ntchito.</p>",
  "studentDialog" : "<p>Awa ndi maphatikizo a malembo. Ndikufunsa kuti uwerenge maphatikizo ochuluka mmene ungathere. Mwachitsanzo, phatikizo ili ndi: &ldquo;go&rdquo;.</p><p><b>Tiye  tiwerenge phatikizo ili:</b> <i>[lozani phatikizo loti &ldquo;kwa&rdquo;]: </i><ul><li><i>[Ngati ophunzira ayankhe molondola, nenani]:</i> <b>Wakhoza, phatikizo ili ndi &ldquo;kwa&ldquo;</b></li> <li><i>[Ngati ophunzira alephere kuyankha molondola, nenani]:</i> <b>phatikizo ili ndi &ldquo;kwa&rdquo;</b></li></ul></p><p><b>Yesa phatikizo lina: werenga phatikizo ili</b> <i>[ lozani phatikizo loti &ldquo;se&rdquo;] </i><ul><li><i>[Ngati ophunzira ayankhe molondola, nenani]:</i><b> Wakhoza, phatikizo ili ndi &ldquo;se&rdquo;</b></li><li><i> [Ngati ophunzira alephere kuyankha molondola, nenani]:</i> <b>phatikizo ili  ndi &ldquo;se&ldquo;  </b></li></ul></p><p><b>Ndikanena kuti yamba, uwerenge maphatikizo mofulumira ndi mosamala. Werenga maphatikizo ali pa mzere uli wonse. Ndikhala chete kukumvetsera pokhapokha ukafuna chithandizo. Kodi ukudziwa zomwe ukuyenera kuchita? Ngati wakonzeka tiye tiyambepo.</b></p>",
  "items": [
    "pe",
    "ye",
    "da",
    "ngi",
    "mbe",
    "yi",
    "ti",
    "no",
    "pa",
    "le",
    "chi",
    "ka",
    "ni",
    "dya",
    "zo",
    "li",
    "ku",
    "ngo",
    "dzi",
    "ndo",
    "e",
    "wu",
    "lo",
    "kwa",
    "si",
    "wi",
    "phu",
    "ri",
    "se",
    "nzi",
    "nkho",
    "fa",
    "go",
    "mi",
    "zi",
    "ra",
    "mfu",
    "mse",
    "po",
    "ya",
    "sa",
    "tho",
    "la",
    "mbo",
    "mda",
    "fi",
    "mo",
    "ta",
    "te",
    "na",
    "nda",
    "nja",
    "mu",
    "pi",
    "ntha",
    "u",
    "na",
    "wa",
    "mnya",
    "lu",
    "va",
    "tsa",
    "i",
    "kho",
    "tu",
    "tsi",
    "da",
    "tso",
    "nga",
    "za",
    "mle",
    "me",
    "ko",
    "yo",
    "ne",
    "cha",
    "mkha",
    "mwa",
    "bwa",
    "thu",
    "ndu",
    "mba",
    "A",
    "mbi",
    "fu",
    "wo",
    "dza",
    "nkha",
    "mphu",
    "ba",
    "ndi",
    "ke",
    "re",
    "Be",
    "ma",
    "ki",
    "nyu",
    "kwe",
    "bwi",
    "o"
  ],
  "_id": "Malawi EGRA Apr 2012.Syllables",

  "couchapp": {
  }
}
